readonly_model/__init__.py
readonly_model/apps.py
readonly_model/dbrouters.py
readonly_model/exceptions.py
readonly_model/settings.py
django_readonly_model-1.2.dist-info/LICENSE.md
django_readonly_model-1.2.dist-info/METADATA
django_readonly_model-1.2.dist-info/WHEEL
django_readonly_model-1.2.dist-info/top_level.txt
django_readonly_model-1.2.dist-info/RECORD
